LICENSE.txt
MANIFEST.in
MetaLocGramN.py
README.txt
setup.py
test.py
MetaLocGramN.egg-info/PKG-INFO
MetaLocGramN.egg-info/SOURCES.txt
MetaLocGramN.egg-info/dependency_links.txt
MetaLocGramN.egg-info/not-zip-safe
MetaLocGramN.egg-info/requires.txt
MetaLocGramN.egg-info/top_level.txt