Metadata-Version: 1.0
Name: MetaLocGramN
Version: 0.99
Summary: MetaLocGramN: a method for subcellular localization prediction of Gram-negative proteins.
Home-page: http://iimcb.genesilico.pl/MetaLocGramN/home
Author: Magnus Marcin, Pawlowski Marcin, Bujnicki Janusz M
Author-email: magnus@genesilico.pl
License: GPLv3
Keywords: bioinformatics,subcellular localization,prediction,gram-negative,sequence,analysis
Platform: UNKNOWN
Classifier: Topic :: Scientific/Engineering :: Bio-Informatics
Classifier: Programming Language :: Python
Classifier: Operating System :: OS Independent
Classifier: Intended Audience :: Science/Research
Classifier: Environment :: Console
